factorial_aivn/__init__.py
factorial_aivn/app.py
factorial_aivn/factorial.py
factorial_aivn_nam-0.1.0.dist-info/METADATA
factorial_aivn_nam-0.1.0.dist-info/WHEEL
factorial_aivn_nam-0.1.0.dist-info/RECORD
